[
    {
        "imageUrl": "https://images-prod.anothermag.com/1035/azure/another-prod/440/6/446183.jpg",
        "info": "Rosalieke is wearing tights in nylon by FALKE. Roserouche 1959 sandals in leather and plastic by VALENTINO GARAVANI"
    },
    {
        "imageUrl": "https://images-prod.anothermag.com/1035/azure/another-prod/440/6/446184.jpg",
        "info": "Pumps in satin and paillettes by GUCCI"
    },
    {
        "imageUrl": "https://images-prod.anothermag.com/1079/azure/another-prod/440/6/446185.jpg",
        "info": "Rosalieke is wearing a headdress with flowers in silk by ANDREAS KRONTHALER FOR VIVIENNE WESTWOOD"
    },
    {
        "imageUrl": "https://images-prod.anothermag.com/1079/azure/another-prod/440/6/446186.jpg",
        "info": "Rosalieke is wearing a suit jacket in matelassé cotton by MIU MIU. Poker Attaché case in aluminium by RIMOWA"
    },
    {
        "imageUrl": "https://images-prod.anothermag.com/1035/azure/another-prod/440/6/446187.jpg",
        "info": "Roe is wearing his own clothes. Phare bag in leather and canvas by LOUIS VUITTON"
    },
    {
        "imageUrl": "https://images-prod.anothermag.com/1035/azure/another-prod/440/6/446188.jpg",
        "info": "Saddle bag in printed denim by DIOR"
    },
    {
        "imageUrl": "https://images-prod.anothermag.com/1079/azure/another-prod/440/6/446189.jpg",
        "info": "Rosalieke is wearing a suitcase bag in nylon by BALENCIAGA"
    },
    {
        "imageUrl": "https://images-prod.anothermag.com/1350/azure/another-prod/440/6/446190.jpg",
        "info": "Squeeze bag in beaded leather by LOEWE"
    },
    {
        "imageUrl": "https://images-prod.anothermag.com/1350/azure/another-prod/440/6/446191.jpg",
        "info": "Rosalieke is wearing sock sandals in viscose and leather and anklets in crystal by JIL SANDER BY LUCIE AND LUKE MEIER"
    },
    {
        "imageUrl": "https://images-prod.anothermag.com/1035/azure/another-prod/440/6/446192.jpg",
        "info": "Sunglasses in plastic and ski goggles in acetate and elastic by TOM FORD. Stylist's own body"
    },
    {
        "imageUrl": "https://images-prod.anothermag.com/1035/azure/another-prod/440/6/446193.jpg",
        "info": "Corsage bag in leather by VAQUERA. Earring in metal by SAINT LAURENT BY ANTHONY VACCARELLO"
    },
    {
        "imageUrl": "https://images-prod.anothermag.com/1080/azure/another-prod/440/6/446194.jpg",
        "info": "Bag in leather and metal by CHANEL"
    },
    {
        "imageUrl": "https://images-prod.anothermag.com/1080/azure/another-prod/440/6/446195.jpg",
        "info": "Gothic bag in leather by DSQUARED2"
    },
    {
        "imageUrl": "https://images-prod.anothermag.com/1035/azure/another-prod/440/6/446196.jpg",
        "info": "1913 bag in re-nylon by PRADA"
    },
    {
        "imageUrl": "https://images-prod.anothermag.com/1350/azure/another-prod/440/6/446197.jpg",
        "info": "Bag in leather with jewellery by COMME DES GARÇONS. SR811 trainers in leather with jewellery by COMME DES GARÇONS X SALOMON"
    },
    {
        "imageUrl": "https://images-prod.anothermag.com/1079/azure/another-prod/440/6/446198.jpg",
        "info": "CD-Player Swipe bag and headphones in plastic by COPERNI"
    },
    {
        "imageUrl": "https://images-prod.anothermag.com/1035/azure/another-prod/440/6/446199.jpg",
        "info": "Jackie 1961 bag in patent leather by GUCCI"
    },
    {
        "imageUrl": "https://images-prod.anothermag.com/1035/azure/another-prod/440/6/446200.jpg",
        "info": "Rosalieke is wearing a tool belt in leather by FENDI"
    },
    {
        "imageUrl": "https://images-prod.anothermag.com/1080/azure/another-prod/440/6/446201.jpg",
        "info": "Wow earrings in aluminium and Elephant cuff in resin by LOEWE X LYNDA BENGLIS"
    },
    {
        "imageUrl": "https://images-prod.anothermag.com/1350/azure/another-prod/440/6/446202.jpg",
        "info": "Beach rackets in cork and ball in rubber by HERMÈS. Earrings with chain in silver with zircon crystals by JIL SANDER BY LUCIE AND LUKE MEIER"
    },
    {
        "imageUrl": "https://images-prod.anothermag.com/1035/azure/another-prod/440/6/446203.jpg",
        "info": "Rosalieke is wearing a pretzel ear cuff in coated brass by D’HEYGERE. Tiffany Victoria earring in platinum with diamonds by TIFFANY & CO"
    }
]
